vaishnavi_exam/__init__.py
vaishnavi_exam/logic.py
vaishnavi_exam-0.1.dist-info/License.txt
vaishnavi_exam-0.1.dist-info/METADATA
vaishnavi_exam-0.1.dist-info/WHEEL
vaishnavi_exam-0.1.dist-info/top_level.txt
vaishnavi_exam-0.1.dist-info/RECORD
