Metadata-Version: 2.1
Name: vaishnavi-exam
Version: 0.1
Summary: The OTT platform package 
Author: Vaishnavi
Author-email: nvaishnavi335@gmail.com
License: MIT
License-File: License.txt
Requires-Dist: pandas
Requires-Dist: requests
